src/__init__.py
src/config.py
src/deploy.py
src/logger.py
src/s3.py
src/server.py
mcp_webpage_to_s3-0.1.3.dist-info/METADATA
mcp_webpage_to_s3-0.1.3.dist-info/WHEEL
mcp_webpage_to_s3-0.1.3.dist-info/entry_points.txt
mcp_webpage_to_s3-0.1.3.dist-info/RECORD
