Metadata-Version: 2.4
Name: mcp-webpage-to-s3
Version: 0.1.3
Summary: MCP Server for deploy html content to S3
Requires-Python: >=3.12
Requires-Dist: boto3>=1.39.1
Requires-Dist: fastmcp>=2.10.0
Requires-Dist: loguru>=0.7.3
Requires-Dist: nanoid>=2.0.0
Requires-Dist: pydantic>=2.0.0
Requires-Dist: pyyaml>=6.0.2
Requires-Dist: typing-extensions>=4.0.0
Provides-Extra: dev
Requires-Dist: pytest>=8.0.0; extra == 'dev'
